Metadata-Version: 2.1
Name: feriados-teste
Version: 5.0.5
Summary: Versão beta não oficial de testes
Author: Luiz Fernando T. Rodrigues
Author-email: euluizfernando2001@gmail.com
License: MIT License
Keywords: feriados br
License-File: LICENSE
